MANIFEST.in
README.rst
requirements.txt
setup.cfg
setup.py
todo.rst
docs/Makefile
docs/source/api-reference.rst
docs/source/conf.py
docs/source/index.rst
docs/source/introduction.rst
docs/source/tutorial.rst
gitgraph/__init__.py
gitgraph/client.py
gitgraph/codec.py
gitgraph/console.py
gitgraph/exceptions.py
gitgraph/meta.py
gitgraph/models.py
gitgraph/query.py
gitgraph/repl.py
gitgraph/server.py
gitgraph/store.py
gitgraph/util.py
gitgraph/version.py
gitgraph.egg-info/PKG-INFO
gitgraph.egg-info/SOURCES.txt
gitgraph.egg-info/dependency_links.txt
gitgraph.egg-info/entry_points.txt
gitgraph.egg-info/not-zip-safe
gitgraph.egg-info/requires.txt
gitgraph.egg-info/top_level.txt