Metadata-Version: 1.0
Name: gitgraph
Version: 0.1.0
Summary: UNKNOWN
Home-page: https://github.com/gabrielfalcao/gitgraph
Author: Gabriel Falcao
Author-email: gabriel@nacaolivre.org
License: UNKNOWN
Platform: UNKNOWN
